[{"place_id": 253495591, "licence": "Data \u00a9 OpenStreetMap contributors, ODbL 1.0. http://osm.org/copyright", "osm_type": "node", "osm_id": 308073351, "lat": "13.0746787", "lon": "77.5056373", "class": "railway", "type": "station", "place_rank": 30, "importance": 5.696269169141707e-05, "addresstype": "railway", "name": "Chikkabanavara", "display_name": "Chikkabanavara, Medarahalli Railway Station Road, Geleyara Balaga Layout, Abbigere, Bengaluru North City Corporation, Bengaluru, Bangalore North, Bengaluru Urban, Karnataka, 560090, India", "boundingbox": ["13.0696787", "13.0796787", "77.5006373", "77.5106373"]}]